odoo/addons/attachment_unindex_content/README.rst
odoo/addons/attachment_unindex_content/__init__.py
odoo/addons/attachment_unindex_content/__manifest__.py
odoo/addons/attachment_unindex_content/hooks.py
odoo/addons/attachment_unindex_content/i18n/attachment_unindex_content.pot
odoo/addons/attachment_unindex_content/i18n/ca.po
odoo/addons/attachment_unindex_content/i18n/es_AR.po
odoo/addons/attachment_unindex_content/models/__init__.py
odoo/addons/attachment_unindex_content/models/ir_attachment.py
odoo/addons/attachment_unindex_content/readme/CONTRIBUTORS.rst
odoo/addons/attachment_unindex_content/readme/DESCRIPTION.rst
odoo/addons/attachment_unindex_content/static/description/icon.png
odoo/addons/attachment_unindex_content/static/description/index.html
odoo14_addon_attachment_unindex_content-14.0.1.0.1.dist-info/METADATA
odoo14_addon_attachment_unindex_content-14.0.1.0.1.dist-info/WHEEL
odoo14_addon_attachment_unindex_content-14.0.1.0.1.dist-info/top_level.txt
odoo14_addon_attachment_unindex_content-14.0.1.0.1.dist-info/RECORD
